{
  "headers": {
    "x-cache": "Hit from cloudfront",
    "access-control-allow-origin": "*",
    "x-frame-options": "DENY",
    "content-security-policy": "default-src 'none'; style-src 'unsafe-inline'; sandbox",
    "etag": "\"9f2f5c5901e054e6e2e00aca8ec39824\"",
    "cross-origin-opener-policy": "same-origin",
    "vary": "Accept-Encoding, Origin",
    "x-amz-cf-pop": "FRA56-P5",
    "x-amz-version-id": "0LSPqipbgx0qYPI5MtVvhv.OKZYd8WK.",
    "cache-control": "public, max-age=31536000, immutable",
    "server": "deno/gcp-europe-west3",
    "content-length": "1879",
    "content-type": "application/typescript; charset=utf-8",
    "age": "22421527",
    "server-timing": "fetchSource;dur=6",
    "last-modified": "Fri, 25 Mar 2022 13:32:48 GMT",
    "via": "http/2 edgeproxy-h",
    "date": "Wed, 27 Dec 2023 23:21:06 GMT",
    "cross-origin-embedder-policy": "same-origin",
    "x-amz-cf-id": "6Kn9exrhCWWemx3lYeTgDn2O0WymyIPoxxrTQBqOpOEJFi3G79lezQ==",
    "x-content-type-options": "nosniff",
    "x-amz-replication-status": "COMPLETED",
    "accept-ranges": "bytes",
    "cross-origin-resource-policy": "same-origin",
    "referrer-policy": "strict-origin-when-cross-origin",
    "strict-transport-security": "max-age=63072000; includeSubDomains; preload"
  },
  "url": "https://deno.land/std@0.132.0/node/_fs/_fs_readlink.ts",
  "now": {
    "secs_since_epoch": 1726140792,
    "nanos_since_epoch": 164866973
  }
}